phis_bin/main.py
phis_bin/配置文件/config.ini
phis_bin-2025.8.4.2.dist-info/METADATA
phis_bin-2025.8.4.2.dist-info/WHEEL
phis_bin-2025.8.4.2.dist-info/entry_points.txt
phis_bin-2025.8.4.2.dist-info/licenses/LICENSE
phis_bin-2025.8.4.2.dist-info/RECORD
