Metadata-Version: 2.4
Name: phis-bin
Version: 2025.8.4.2
Summary: browser binary files
License-File: LICENSE
Requires-Python: >=3.10
